{"wh": 9, "mccain": 34, "fox": 22, "news": 59, "cuts": 11, "general": 15, "called": 33, "john": 48, "white": 56, "house": 55, "joke": 7, "help": 105, "north": 31, "korea": 19, "economy": 8, "gives": 15, "says": 56, "trump": 180, "tweet": 18, "words": 15, "illegal": 14, "paul": 17, "calls": 13, "life": 57, "public": 37, "hit": 15, "plan": 22, "lower": 8, "drug": 12, "prices": 11, "expect": 9, "korean": 14, "release": 14, "bond": 5, "market": 13, "economic": 13, "continues": 6, "push": 7, "congress": 18, "job": 42, "complete": 14, "budget": 7, "scott": 11, "signs": 5, "cia": 23, "director": 16, "nominee": 6, "promote": 10, "community": 7, "joe": 16, "family": 32, "hits": 5, "aide": 15, "meghan": 5, "dismisses": 7, "opposition": 7, "saying": 27, "dying": 8, "michael": 43, "cohen": 14, "knew": 13, "allegations": 6, "new": 403, "york": 12, "court": 8, "filing": 11, "senator": 17, "wants": 27, "tax": 84, "children": 17, "politics": 16, "fear": 10, "just": 329, "daughter": 11, "say": 79, "kelly": 5, "keeping": 7, "daca": 6, "join": 46, "senate": 14, "republican": 14, "lunch": 7, "death": 12, "week": 82, "song": 5, "business": 118, "meeting": 17, "american": 51, "leadership": 11, "initiative": 7, "act": 16, "vote": 27, "haspel": 5, "head": 13, "program": 24, "speaks": 7, "rise": 9, "rest": 22, "live": 112, "power": 37, "small": 24, "lie": 9, "focus": 10, "nuclear": 10, "provides": 7, "welcome": 18, "change": 54, "political": 27, "lead": 11, "attacking": 5, "liberal": 33, "win": 27, "country": 35, "global": 20, "health": 18, "security": 21, "gop": 14, "president": 82, "terrible": 7, "normal": 5, "donnelly": 5, "immigration": 7, "hard": 28, "home": 57, "takes": 11, "aim": 5, "work": 59, "time": 99, "according": 9, "tweets": 11, "women": 37, "making": 25, "history": 19, "chief": 8, "hiring": 8, "questions": 9, "make": 99, "promise": 6, "violence": 10, "girls": 6, "justice": 18, "swamp": 8, "thing": 38, "sarah": 8, "regret": 5, "running": 25, "primary": 11, "performance": 9, "financial": 10, "race": 9, "energy": 10, "pruitt": 5, "ban": 6, "days": 43, "tom": 7, "payment": 28, "looks": 41, "like": 288, "money": 35, "daily": 7, "willing": 8, "walk": 6, "away": 26, "speech": 11, "kamala": 8, "harris": 7, "finally": 23, "marijuana": 6, "end": 24, "federal": 34, "facebook": 24, "ad": 7, "shows": 29, "true": 30, "influence": 7, "official": 31, "father": 8, "sources": 5, "republicans": 24, "media": 34, "potential": 5, "supreme": 5, "supports": 9, "credit": 6, "names": 6, "wrong": 29, "west": 12, "fight": 20, "department": 9, "learn": 25, "california": 19, "democratic": 14, "letter": 7, "row": 5, "talks": 7, "got": 86, "right": 105, "probably": 20, "took": 16, "mike": 19, "goes": 18, "prison": 6, "showing": 11, "russian": 18, "little": 34, "looking": 325, "taken": 11, "single": 16, "russians": 5, "want": 160, "best": 68, "solution": 6, "love": 117, "come": 60, "ice": 11, "need": 218, "held": 11, "does": 82, "meant": 7, "door": 10, "dumb": 7, "mueller": 15, "control": 19, "million": 11, "steve": 5, "bring": 27, "lives": 10, "teachers": 18, "arrested": 8, "better": 105, "fair": 8, "charge": 7, "people": 145, "problem": 22, "guess": 16, "sex": 13, "following": 13, "quite": 8, "happens": 5, "way": 72, "it?": 27, "gonna": 18, "son": 9, "schools": 7, "inside": 12, "powerful": 11, "answer": 37, "student": 63, "prayers?": 24, "oddsmonkey": 36, "tip": 38, "scales": 36, "favour": 36, "huffington": 31, "post": 102, "discusses": 20, "matched": 18, "betting": 18, "wait": 51, "load": 25, "think": 124, "u": 49, "open": 23, "ur": 16, "big": 41, "sick": 10, "arrest": 7, "george": 14, "democrat": 12, "party": 16, "men": 11, "n": 9, "maybe": 25, "sure": 51, "return": 9, "typical": 8, "total": 8, "feed": 76, "happy": 101, "yes": 26, "course": 16, "common": 20, "sense": 17, "start": 47, "helping": 11, "comes": 13, "bad": 48, "movie": 15, "old": 39, "r": 15, "w": 5, "god": 101, "amen": 16, "bless": 7, "acting": 7, "trust": 20, "great": 118, "day": 99, "mr": 19, "talk": 35, "deserves": 8, "peace": 20, "pathetic": 6, "human": 12, "step": 10, "times": 16, "thought": 74, "ago": 11, "came": 13, "free": 50, "hey": 36, "rt": 5, "birthday": 18, "thanks": 133, "latest": 28, "topics": 16, "good": 321, "jesus": 9, "christ": 18, "stage": 16, "proud": 24, "thank": 110, "recently": 14, "engaged": 14, "followers": 67, "brought": 10, "rock": 5, "gorgeous": 11, "car": 8, "forget": 19, "look": 72, "pick": 12, "influencers": 6, "grow": 12, "twitter": 26, "seeing": 18, "recent": 6, "order": 101, "huge": 6, "photos": 5, "using": 30, "successful": 9, "blog": 54, "jeff": 7, "members": 18, "tools": 6, "create": 28, "tips": 17, "succeed": 6, "hustle": 6, "hrs": 8, "later": 17, "beautiful": 65, "coffee": 5, "absolutely": 17, "spring": 8, "wish": 32, "green": 18, "couple": 9, "check": 397, "actually": 42, "hi": 16, "trying": 39, "use": 76, "code": 21, "received": 10, "online": 15, "telling": 10, "game": 24, "crazy": 9, "sold": 7, "places": 8, "share": 14, "site": 7, "ways": 9, "congrats": 16, "dirty": 11, "laptops": 5, "important": 18, "clean": 16, "laptop": 8, "|": 35, "tech": 67, "girl": 57, "google": 88, "pixelbook": 5, "finding": 10, "fixing": 6, "cold": 8, "spots": 5, "blindspotz": 5, "things": 39, "prepare": 7, "vacation": 10, "consider": 17, "healthy": 11, "planning": 15, "basement": 6, "finishing": 6, "project": 13, "choosing": 5, "outdoor": 7, "camera": 8, "building": 18, "red": 20, "diy": 5, "hand": 25, "baby": 17, "truly": 10, "believe": 44, "hope": 46, "kid": 10, "shopping": 5, "gift": 7, "based": 17, "friends": 23, "today": 131, "golden": 9, "state": 63, "killer": 8, "gone": 9, "watch": 45, "lot": 29, "minutes": 13, "impossible": 7, "hold": 14, "definitely": 17, "awesome": 234, "blessings": 13, "black": 28, "matter": 18, "face": 15, "appreciate": 13, "going": 110, "respect": 8, "s": 6, "m": 21, "h": 5, "social": 17, "fact": 25, "remains": 6, "working": 20, "read": 62, "fired": 7, "episode": 13, "paying": 9, "citizens": 12, "south": 72, "curious": 5, "gun": 30, "chicago": 10, "happening": 11, "park": 17, "stuff": 9, "watching": 27, "police": 17, "means": 18, "major": 16, "man": 46, "til": 6, "add": 11, "send": 12, "jones": 8, "mother": 14, "killed": 7, "night": 23, "wife": 13, "worry": 13, "coming": 25, "gang": 5, "cops": 8, "lied": 5, "vice": 11, "o": 6, "p": 8, "exactly": 15, "higher": 83, "place": 19, "currently": 11, "gotta": 10, "world": 47, "living": 12, "turn": 18, "buy": 23, "church": 14, "june": 5, "makes": 31, "high": 35, "far": 115, "nice": 37, "facts": 16, "feel": 32, "number": 53, "friend": 16, "posted": 21, "worth": 20, "plus": 7, "dance": 5, "honored": 6, "national": 21, "feeling": 16, "know": 168, "cover": 9, "hours": 68, "saw": 24, "female": 6, "went": 15, "moved": 6, "year": 29, "stuck": 6, "nature": 8, "agent": 5, "video": 84, "uploaded": 9, "snow": 5, "wearing": 8, "afternoon": 5, "run": 26, "hear": 34, "companies": 17, "caught": 8, "special": 20, "shout": 5, "helped": 6, "classroom": 5, "outside": 8, "forced": 7, "queen": 7, "b": 6, "tell": 40, "east": 7, "apartment": 7, "tried": 6, "hair": 7, "wishing": 7, "submit": 7, "real": 35, "struggle": 7, "left": 21, "agree": 28, "reason": 19, "echo": 12, "chamber": 11, "wake": 9, "amazing": 24, "ability": 7, "tells": 5, "muslim": 16, "leave": 17, "mention": 9, "disaster": 6, "question": 16, "seriously": 7, "prove": 12, "entire": 13, "piece": 9, "january": 5, "trade": 12, "wanted": 17, "european": 5, "close": 17, "kind": 36, "doj": 8, "years": 41, "cash": 11, "follow": 27, "road": 9, "point": 17, "military": 8, "imagine": 7, "wealthy": 5, "congratulations": 11, "remember": 22, "obama": 42, "admin": 5, "repeatedly": 5, "completely": 14, "progressive": 5, "foreign": 8, "policy": 17, "establishment": 6, "difference": 10, "administration": 15, "dangerous": 5, "platform": 10, "defend": 5, "threat": 6, "force": 9, "middle": 15, "attacks": 10, "funded": 6, "apparently": 10, "enemy": 5, "longer": 6, "guys": 16, "attempts": 5, "destroy": 8, "playing": 5, "feels": 6, "school": 73, "flag": 8, "stand": 18, "principles": 15, "excellent": 7, "interview": 19, "service": 24, "deal": 31, "able": 17, "confidence": 7, "reality": 10, "team": 30, "form": 6, "choice": 7, "sign": 17, "international": 18, "role": 10, "center": 17, "idea": 13, "statement": 9, "press": 11, "executive": 7, "united": 30, "comey": 9, "truth": 19, "damage": 9, "america": 83, "law": 33, "value": 12, "doing": 36, "said": 49, "line": 12, "fbi": 16, "agents": 6, "civil": 7, "failed": 7, "response": 8, "short": 8, "kerry": 7, "support": 42, "gave": 20, "personal": 18, "wonder": 17, "luck": 14, "choose": 10, "states": 27, "position": 6, "attack": 8, "activities": 6, "conservative": 15, "worst": 8, "pulling": 6, "democrats": 27, "getting": 52, "remain": 6, "exchange": 10, "provide": 10, "regime": 8, "war": 26, "person": 23, "leading": 17, "attempt": 6, "iranian": 6, "including": 8, "break": 8, "food": 15, "tonight": 23, "michelle": 7, "rep": 5, "customer": 5, "hour": 11, "try": 26, "disappointed": 6, "closed": 66, "level": 7, "drive": 5, "chicken": 5, "experience": 10, "told": 8, "really": 72, "what?": 6, "ok": 20, "moment": 10, "flight": 7, "plane": 6, "fake": 31, "missing": 8, "spent": 12, "starting": 16, "fitness": 5, "given": 9, "bar": 17, "employee": 5, "word": 11, "dog": 6, "pay": 40, "politicians": 8, "lol": 32, "known": 10, "month": 14, "morning": 19, "session": 5, "bank": 13, "active": 6, "wave": 5, "joy": 10, "staff": 8, "il": 5, "billion": 8, "card": 21, "everybody": 8, "voted": 13, "racist": 6, "asked": 9, "poor": 12, "pretty": 17, "funny": 8, "changed": 5, "el": 5, "figure": 7, "kids": 29, "parents": 12, "date": 12, "ask": 30, "kinda": 8, "sexual": 5, "yo": 5, "elephant": 6, "having": 23, "waiting": 15, "prime": 5, "pray": 12, "network": 9, "long": 53, "mean": 26, "treated": 6, "treat": 6, "folks": 7, "sorry": 20, "fights": 5, "yea": 6, "tv": 11, "damn": 15, "games": 9, "claim": 14, "wanna": 10, "boy": 17, "missed": 11, "you?": 9, "beat": 11, "fall": 20, "chinese": 14, "ready": 17, "relationship": 8, "lost": 18, "mind": 20, "iran": 18, "signed": 9, "stop": 50, "russia": 26, "private": 13, "don": 5, "calling": 19, "journalist": 6, "cnn": 19, "protect": 12, "sessions": 7, "deep": 13, "lady": 12, "hate": 24, "list": 13, "keeps": 6, "growing": 11, "lies": 6, "yeah": 22, "stupid": 7, "member": 8, "gets": 18, "eyes": 5, "quickly": 5, "woman": 13, "bet": 7, "worked": 10, "quit": 12, "obviously": 7, "art": 17, "votes": 5, "porn": 7, "star": 8, "impeach": 8, "rich": 8, "spend": 9, "message": 13, "low": 11, "liberals": 16, "internet": 9, "easily": 8, "?": 117, "brain": 8, "dollar": 7, "popular": 8, "false": 9, "path": 6, "laugh": 8, "taking": 30, "fighting": 14, "shame": 6, "msm": 5, "double": 6, "standard": 8, "candace": 5, "standing": 10, "deserve": 10, "success": 9, "sending": 5, "legacy": 6, "dead": 12, "months": 8, "driving": 9, "lets": 6, "flip": 7, "hillary": 13, "clinton": 15, "dollars": 5, "blocked": 8, "strength": 6, "planned": 6, "needs": 38, "disease": 5, "relations": 5, "interested": 51, "stormy": 11, "easy": 16, "legal": 13, "owner": 9, "issue": 7, "laws": 15, "bias": 7, "file": 6, "music": 41, "mission": 5, "passed": 6, "totally": 9, "criminal": 8, "film": 26, "van": 5, "snyder": 5, "brothers": 5, "ca": 6, "jaime": 9, "space": 9, "science": 34, "glad": 16, "knowing": 6, "gold": 9, "thinks": 6, "mouth": 8, "offer": 111, "local": 13, "knows": 12, "murder": 5, "dna": 5, "talking": 26, "restraining": 5, "mental": 7, "strong": 14, "despite": 7, "sweet": 6, "extra": 7, "similar": 6, "current": 12, "merry": 8, "record": 14, "freedom": 5, "used": 28, "signature": 16, "meet": 28, "remind": 6, "met": 11, "happen": 9, "types": 10, "engaging": 5, "clearly": 7, "town": 8, "fuck": 12, "fix": 8, "posting": 5, "govt": 7, "price": 6, "previous": 12, "final": 6, "speak": 18, "logo": 233, "continue": 11, "illegally": 6, "body": 13, "cta": 17, "tariffs": 10, "hurt": 7, "technology": 17, "built": 14, "internship": 5, "industry": 8, "creating": 5, "committee": 6, "excited": 13, "loved": 12, "data": 16, "allow": 8, "millions": 9, "jobs": 8, "thrilled": 6, "revolution": 5, "digital": 14, "bringing": 6, "future": 14, "intelligence": 5, "solve": 5, "concept": 6, "developed": 5, "study": 19, "impact": 8, "felt": 70, "thousands": 7, "innovative": 8, "vr": 6, "area": 11, "sector": 5, "leaders": 11, "mobile": 6, "solutions": 5, "cost": 11, "seven": 6, "set": 20, "created": 18, "smart": 27, "views": 7, "ai": 8, "care": 38, "learned": 12, "career": 11, "age": 9, "thinking": 12, "research": 20, "physical": 9, "countries": 5, "diverse": 10, "uses": 6, "quality": 5, "increase": 9, "china": 70, "contact": 11, "standards": 5, "johnson": 6, "government": 35, "goal": 7, "machine": 6, "learning": 12, "housing": 5, "heart": 21, "rate": 9, "policies": 9, "saved": 5, "kicked": 5, "opening": 10, "french": 6, "visit": 22, "blockchain": 11, "hill": 5, "information": 11, "sharing": 8, "healthcare": 6, "innovation": 5, "awards": 5, "services": 14, "app": 7, "helps": 16, "identify": 5, "planet": 8, "listed": 5, "stock": 6, "favorite": 15, "save": 13, "young": 17, "cool": 18, "discuss": 5, "search": 10, "decision": 15, "taxes": 15, "products": 5, "kim": 10, "jong": 7, "book": 26, "leader": 17, "border": 9, "begin": 9, "lord": 16, "governor": 17, "delivers": 5, "barbara": 10, "late": 12, "bush": 5, "israel": 13, "incredible": 9, "stay": 19, "hands": 7, "sunday": 9, "photo": 10, "pm": 18, "fan": 5, "dear": 11, "minute": 5, "simply": 7, "greatest": 18, "christmas": 15, "harry": 5, "mom": 5, "donald": 21, "king": 32, "attention": 11, "changing": 5, "argument": 9, "case": 19, "college": 8, "students": 30, "guy": 22, "famous": 6, "prageru": 6, "americans": 15, "gear": 6, "culture": 6, "story": 11, "reform": 5, "faith": 8, "education": 25, "receives": 6, "explain": 5, "allowed": 9, "accept": 5, "university": 10, "supporting": 25, "represent": 9, "attending": 5, "sounds": 14, "pence": 13, "supposed": 7, "conservatives": 9, "century": 5, "privacy": 6, "isis": 7, "hot": 12, "workers": 5, "programs": 70, "fb": 8, "washington": 7, "miss": 24, "group": 7, "raw": 5, "conference": 5, "privilege": 5, "article": 15, "spot": 12, "box": 7, "northern": 12, "crime": 5, "organization": 6, "player": 5, "lying": 12, "sad": 16, "august": 23, "lien": 23, "filed": 25, "avenatti": 30, "personally": 18, "joined": 13, "greene": 11, "broillet": 11, "los": 14, "angeles": 14, "boutique": 9, "litigation": 7, "cop": 5, "build": 13, "hell": 19, "wall": 9, "giving": 12, "tired": 15, "taxpayers": 5, "sell": 10, "company": 24, "killing": 5, "investigation": 10, "crystal": 5, "election": 22, "doors": 13, "different": 14, "andrew": 8, "broke": 6, "works": 14, "playlist": 6, "gallery": 22, "checkout": 18, "sale": 13, "society": 6, "style": 9, "inspired": 7, "celadon": 5, "elegant": 16, "thailand": 6, "thai": 5, "natural": 8, "blue": 11, "fat": 5, "coral": 5, "buying": 6, "color": 19, "lack": 7, "coverage": 12, "amid": 6, "revealed": 5, "mayor": 9, "convicted": 5, "conspiracy": 7, "mark": 11, "levin": 5, "dems": 17, "remove": 20, "judge": 11, "info": 8, "claims": 11, "past": 10, "reid": 6, "perfect": 16, "picture": 24, "ahead": 5, "released": 5, "property": 20, "setting": 5, "florida": 5, "shot": 14, "turns": 8, "critical": 6, "hoping": 7, "documents": 10, "capable": 8, "victim": 5, "massive": 6, "putting": 12, "cut": 13, "growth": 8, "robert": 6, "investigate": 5, "raises": 7, "effort": 5, "ny": 7, "safety": 8, "da": 6, "report": 83, "paid": 16, "named": 5, "illinois": 10, "debate": 5, "teacher": 8, "mexico": 13, "amendment": 6, "rights": 9, "faced": 11, "tough": 5, "dallas": 6, "nra": 10, "review": 21, "responsible": 6, "kanye": 12, "puts": 5, "offers": 5, "serving": 9, "design": 577, "professional": 129, "gig": 105, "eddm": 105, "postcard": 159, "type": 76, "usa": 7, "series": 20, "super": 5, "lil": 16, "straight": 8, "dm": 6, "positive": 6, "listen": 12, "turned": 9, "sit": 8, "phone": 13, "evil": 15, "phd": 5, "x": 18, "situation": 6, "involved": 7, "angry": 5, "heard": 16, "shall": 8, "afraid": 10, "teaching": 8, "seen": 23, "secretary": 10, "kept": 9, "summer": 8, "early": 13, "content": 6, "protest": 7, "event": 15, "usually": 5, "creative": 18, "excuse": 7, "ppl": 6, "irs": 16, "chance": 11, "child": 13, "smh": 10, "reporting": 5, "cause": 18, "opportunity": 11, "kill": 13, "safe": 9, "african": 5, "stopped": 6, "dude": 5, "campaign": 24, "wtf": 13, "notice": 5, "enjoying": 9, "sun": 7, "ass": 18, "ma": 6, "play": 17, "office": 12, "click": 139, "upcoming": 6, "think?": 40, "loves": 12, "account": 12, "rude": 6, "thats": 8, "understand": 15, "dont": 13, "bs": 5, "won": 10, "shooting": 5, "water": 13, "biggest": 12, "lots": 11, "older": 6, "city": 17, "files": 19, "trouble": 5, "professor": 5, "page": 19, "added": 8, "fast": 6, "possible": 7, "download": 5, "represents": 11, "wikipedia": 5, "depends": 5, "edit": 15, "related": 5, "trip": 6, "fun": 9, "this?": 6, "dream": 68, "habit": 41, "that?": 9, "interesting": 10, "containers": 9, "reasons": 6, "source": 8, "recognize": 5, "especially": 7, "clear": 8, "bit": 5, "disgusting": 7, "saturday": 12, "term": 13, "decided": 7, "unless": 7, "somebody": 7, "raid": 6, "cares": 5, "shit": 5, "mess": 5, "realize": 10, "compassion": 5, "profit": 6, "suppose": 5, "breaking": 6, "example": 5, "certified": 12, "naked": 8, "independent": 5, "why?": 8, "drop": 8, "require": 5, "available": 19, "lose": 9, "televisa": 7, "announced": 7, "broadcast": 52, "presidential": 5, "proposals": 5, "document": 8, "spending": 5, "identity": 7, "nearly": 6, "include": 6, "client": 6, "brother": 7, "pope": 7, "april": 12, "comment": 5, "opinion": 8, "largest": 7, "reach": 9, "evidence": 17, "actions": 8, "confirm": 5, "weeks": 5, "walker": 5, "wins": 6, "wisconsin": 13, "sister": 11, "council": 5, "pull": 5, "british": 5, "correct": 5, "surprised": 11, "shut": 9, "sweden": 5, "climate": 6, "prosperity": 5, "eye": 16, "instead": 6, "royal": 6, "happened": 11, "net": 7, "capital": 6, "commercial": 5, "exclusive": 24, "worse": 5, "steps": 8, "fannie": 5, "guns": 8, "philip": 6, "alex": 5, "analysis": 7, "taylor": 6, "peter": 15, "fail": 6, "james": 13, "crowd": 5, "nation": 8, "enjoyed": 5, "speaking": 13, "enjoy": 14, "leo": 38, "wedding": 6, "finger": 5, "charged": 5, "flat": 54, "closer": 5, "listening": 31, "likely": 5, "ward": 11, "winning": 13, "designated": 5, "bible": 12, "walks": 5, "unique": 44, "defeat": 5, "prepared": 9, "access": 10, "wonderful": 8, "favor": 6, "celebrate": 6, "dare": 5, "problems": 6, "limits": 5, "earth": 6, "begins": 6, "soon": 15, "meaning": 6, "organizations": 6, "stephen": 6, "receive": 6, "light": 8, "newest": 9, "henry": 6, "ones": 5, "syrian": 5, "rules": 7, "syria": 10, "register": 5, "strike": 5, "view": 5, "develop": 7, "large": 8, "second": 12, "sir": 10, "bye": 7, "temple": 5, "march": 11, "historic": 6, "season": 6, "blowing": 5, "main": 5, "forever": 5, "liked": 31, "victory": 17, "insurance": 9, "proves": 5, "hidden": 8, "stone": 11, "agency": 5, "equal": 8, "smoke": 7, "richard": 14, "roman": 113, "funds": 12, "smithsonian": 19, "experts": 13, "featuring": 12, "tomorrow": 19, "started": 11, "resources": 6, "honor": 9, "individuals": 6, "movement": 6, "weather": 9, "dc": 6, "graphic": 31, "stem": 5, "hall": 5, "booth": 6, "accepting": 5, "training": 5, "diversity": 6, "lesson": 69, "francine": 6, "joint": 7, "approach": 5, "ft": 7, "application": 5, "crypto": 9, "software": 5, "die": 65, "intelligent": 6, "terms": 6, "bitcoin": 9, "ring": 11, "institutions": 47, "generation": 5, "half": 10, "reading": 5, "abolish": 5, "corrupt": 14, "chose": 8, "right?": 7, "constitution": 5, "colleges": 17, "tickets": 25, "starts": 6, "challenge": 6, "indictments": 6, "hospitals": 5, "award": 6, "ha": 6, "heavy": 5, "creepy": 5, "class": 12, "profile": 14, "forgot": 6, "blah": 5, "forward": 8, "ticket": 5, "purchase": 5, "fellow": 6, "fucking": 6, "link": 149, "letterhead": 10, "stationery": 9, "serve": 8, "liar": 6, "amazon": 9, "simple": 17, "dnc": 8, "candidates": 7, "hearing": 5, "concerned": 7, "antifa": 5, "downtown": 5, "leaked": 5, "emails": 7, "candidate": 9, "texts": 5, "e": 8, "savage": 5, "extremely": 7, "im": 11, "ya": 14, "pro": 6, "original": 6, "modern": 16, "j": 5, "regarding": 7, "developer": 225, "kick": 7, "wing": 5, "risk": 16, "accounts": 7, "egyptian": 12, "manager": 5, "county": 6, "fool": 7, "f": 8, "assistance": 5, "saudi": 7, "delete": 5, "insight": 5, "exact": 5, "extreme": 8, "advantage": 5, "stands": 5, "adjusters": 5, "benefit": 5, "unite": 11, "celebrating": 8, "playstation": 50, "classic": 15, "debbie": 5, "smoking": 11, "adam": 11, "evans": 6, "annual": 64, "logistics": 6, "thread": 7, "cyber": 8, "roy": 9, "pass": 6, "secret": 8, "block": 5, "crooked": 5, "theory": 5, "g": 8, "uno": 6, "dos": 6, "studies": 6, "chengdu": 6, "evening": 52, "dinner": 9, "raise": 5, "issues": 6, "claimed": 5, "fort": 12, "district": 5, "vintage": 9, "rams": 9, "msu": 6, "vatican": 5, "association": 6, "terrified": 5, "lango": 6, "speed": 6, "monday": 5, "hypocrisy": 5, "alfie": 6, "jackson": 6, "demand": 6, "hpm": 7, "sheikh": 8, "hasina": 6, "bangladesh": 5, "india": 10, "attractive": 16, "email": 6, "vs": 9, "test": 6, "sports": 6, "wwe": 17, "larry": 5, "wrestling": 6, "wallet": 5, "fans": 7, "billy": 5, "jail": 5, "morgan": 7, "ohh": 6, "quick": 5, "beth": 8, "marketing": 7, "scam": 7, "collected": 48, "wrestlemania": 11, "undertaker": 15, "ruby": 7, "valentine": 9, "foster": 57, "web": 226, "responsive": 225, "html": 221, "website?": 217, "libtards": 5, "indian": 10, "fiverr": 14, "cultural": 7, "trading": 5, "collectors": 110, "ancient": 110, "coins": 109, "vector": 29, "hello": 50, "decentralized": 6, "youth": 42, "ed": 61, "youth?": 15, "reviewing": 18, "offering": 6, "included": 34, "sudan": 10, "visa": 6, "refund": 6, "sudanese": 5, "tortured": 7, "flower": 5, "milwaukee": 10, "angela": 21, "jenkins": 10, "films": 9, "selected": 5, "theatre": 9, "fowler": 7, "ultimate": 5, "logomekars": 93, "monogram": 13, "feminine": 6, "minimal": 15, "gigs": 13, "retro": 7, "mekars": 7, "nazmul_bd_gd": 102, "convert": 6, "raster": 6, "blurred": 7, "image": 9, "upc": 14, "ean": 14, "illustrator": 30, "adobe": 14, "background": 15, "effect": 11, "work?": 7, "design?": 25, "prezi": 5, "commentary": 17, "sos": 8, "huey": 7, "moore": 5, "request": 5, "yankee": 7, "cannabis": 7, "audio": 9, "~black": 6, "catching": 9, "liuba": 17, "grechen": 13, "shirley": 6, "pete": 10, "fundraising": 8, "unseat": 9, "japan": 62, "ji": 11, "tail": 5, "joining": 9, "edst": 5, "pandit": 20, "pandits": 7, "goddess": 7, "mukhi": 19, "rudraksha": 19, "sapphire": 6, "gemstones": 21, "emerald": 7, "gemstone": 18, "puja": 6, "moonga": 7, "combination": 5, "mala": 5, "shankh": 9, "yantra": 6, "yumerium": 6, "payportal": 9, "loandex": 6, "wemark": 5, "token": 9, "entry": 6}